sosw/__init__.py
sosw/app.py
sosw/essential.py
sosw/labourer.py
sosw/orchestrator.py
sosw/scavenger.py
sosw/scheduler.py
sosw/worker.py
sosw/worker_assistant.py
sosw/components/__init__.py
sosw/components/benchmark.py
sosw/components/config.py
sosw/components/decorators.py
sosw/components/dynamo_db.py
sosw/components/exceptions.py
sosw/components/helpers.py
sosw/components/siblings.py
sosw/components/sigv4.py
sosw/components/sns.py
sosw/managers/__init__.py
sosw/managers/ecology.py
sosw/managers/meta_handler.py
sosw/managers/task.py
sosw-0.7.51.dist-info/licenses/LICENSE
sosw-0.7.51.dist-info/licenses/NOTICE
sosw-0.7.51.dist-info/METADATA
sosw-0.7.51.dist-info/WHEEL
sosw-0.7.51.dist-info/top_level.txt
sosw-0.7.51.dist-info/RECORD
