Metadata-Version: 2.4
Name: sosw
Version: 0.7.51
Summary: Serverless Orchestrator of Serverless Workers
Home-page: http://github.com/sosw/sosw
Author: Nikolay Grishchenko
Author-email: ngr@sosw.app
License: MIT
Classifier: Development Status :: 5 - Production/Stable
Classifier: Operating System :: Other OS
Classifier: License :: OSI Approved :: MIT License
Classifier: Programming Language :: Python :: 3.10
Classifier: Programming Language :: Python :: 3.11
Classifier: Programming Language :: Python :: 3.12
Classifier: Programming Language :: Python :: 3.13
Classifier: Topic :: Software Development
License-File: LICENSE
License-File: NOTICE
Requires-Dist: boto3>=1.35.0
Dynamic: author
Dynamic: author-email
Dynamic: classifier
Dynamic: description
Dynamic: description-content-type
Dynamic: home-page
Dynamic: license
Dynamic: license-file
Dynamic: requires-dist
Dynamic: summary
